{
    "issues": [
        {
            "id": 30185,
            "project": {
                "id": 491,
                "name": "Mail Trade CRM v.2"
            },
            "tracker": {
                "id": 5,
                "name": "Feature"
            },
            "status": {
                "id": 8,
                "name": "Done"
            },
            "priority": {
                "id": 4,
                "name": "\u041d\u043e\u0440\u043c\u0430\u043b\u044c\u043d\u044b\u0439"
            },
            "author": {
                "id": 428,
                "name": "A. Zharikov"
            },
            "assigned_to": {
                "id": 428,
                "name": "A. Zharikov"
            },
            "fixed_version": {
                "id": 1789,
                "name": "Back CRM"
            },
            "subject": "\u0414\u043e\u0431\u0430\u0432\u0438\u0442\u044c \u043f\u0430\u0440\u0430\u043c\u0435\u0442\u0440\u044b \u0434\u043b\u044f \u0444\u0438\u043b\u044c\u0442\u0440\u0430\u0446\u0438\u0438 \u0446\u0435\u043f\u043e\u0447\u0435\u043a",
            "description": "\u0417\u0430\u043f\u0440\u043e\u0441:\r\nhttp://135.181.153.78:8000/api/chains-letters?direction&page=1&per_page=15&sort\r\n\u0432\u043e\u0437\u0432\u0440\u0430\u0449\u0430\u0435\u0442 \u043d\u0430\u043c 2 \u043c\u0430\u0441\u0441\u0438\u0432\u0430 (items \u0438 publicItems), \u043a\u0430\u0436\u0434\u044b\u0439 \u043c\u0430\u0441\u0441\u0438\u0432 \u0440\u0435\u043d\u0434\u0435\u0440\u0438\u0442\u0441\u044f \u0432 \u043e\u0442\u0434\u0435\u043b\u044c\u043d\u0443\u044e \u0442\u0430\u0431\u043b\u0438\u0446\u0443 \u0441\u043e \u0441\u0432\u043e\u0435\u0439 \u043f\u0430\u0433\u0438\u043d\u0430\u0446\u0438\u0435\u0439.\r\n\u041d\u0435\u043e\u0431\u0445\u043e\u0434\u0438\u043c\u043e \u0434\u043e\u0431\u0430\u0432\u0438\u0442\u044c \u043f\u0430\u0440\u0430\u043c\u0435\u0442\u0440\u044b \u0432 \u0437\u0430\u043f\u0440\u043e\u0441 \u0434\u043b\u044f \u0444\u0438\u043b\u044c\u0442\u0440\u0430\u0446\u0438\u0438 \u043c\u0430\u0441\u0441\u0438\u0432\u0430 publicItems",
            "start_date": "2022-03-25",
            "done_ratio": 100,
            "created_on": "2022-03-25T11:41:07Z",
            "updated_on": "2022-03-25T11:47:50Z"
        },
        {
            "id": 30184,
            "project": {
                "id": 491,
                "name": "Mail Trade CRM v.2"
            },
            "tracker": {
                "id": 5,
                "name": "Feature"
            },
            "status": {
                "id": 1,
                "name": "New"
            },
            "priority": {
                "id": 5,
                "name": "\u0412\u044b\u0441\u043e\u043a\u0438\u0439"
            },
            "author": {
                "id": 433,
                "name": "A. Stratan"
            },
            "assigned_to": {
                "id": 428,
                "name": "A. Zharikov"
            },
            "fixed_version": {
                "id": 1788,
                "name": "Front CRM"
            },
            "parent": {
                "id": 30182
            },
            "subject": "Chains: \u0418\u0441\u043f\u0440\u0430\u0432\u0438\u0442\u044c \u0442\u0435\u043a\u0441\u0442 \u043f\u043e\u044f\u0441\u043d\u0435\u043d\u0438\u044f \u0434\u043b\u044f \u043f\u043e\u043b\u044f match",
            "description": "\u0422\u0435\u043a\u0441\u0442 \"\u0418\u0441\u043f\u043e\u043b\u044c\u0437\u043e\u0432\u0430\u0442\u044c \u0441\u043e\u0431\u0441\u0442\u0432\u0435\u043d\u043d\u043e\u0435 \u0440\u0430\u0441\u043f\u0438\u0441\u0430\u043d\u0438\u0435 \u0434\u043b\u044f \u043e\u0442\u043f\u0440\u0430\u0432\u043a\u0438 \u043f\u0438\u0441\u044c\u043c\u0430\" \u0438\u0441\u043f\u0440\u0430\u0432\u0438\u0442\u044c\r\n\u041d\u0430 \"\u0418\u0433\u043d\u043e\u0440\u0438\u0440\u043e\u0432\u0430\u0442\u044c \u043e\u0441\u043d\u043e\u0432\u043d\u043e\u0435 \u0440\u0430\u0441\u043f\u0438\u0441\u0430\u043d\u0438\u0435 \u0432 \u0446\u0435\u043f\u043e\u0447\u043a\u0435\"\r\n\r\n*\u0428\u0430\u0433\u0438:* (login admin)\r\n\r\n# http://135.181.90.157/letter_fragments_and_templates\r\n# \u0414\u043e\u0431\u0430\u0432\u0438\u0442\u044c \u0441\u043e\u043e\u0431\u0449\u0435\u043d\u0438\u0435",
            "start_date": "2022-03-25",
            "done_ratio": 0,
            "created_on": "2022-03-25T11:20:39Z",
            "updated_on": "2022-03-25T11:20:39Z"
        },
        {
            "id": 30179,
            "project": {
                "id": 491,
                "name": "Mail Trade CRM v.2"
            },
            "tracker": {
                "id": 5,
                "name": "Feature"
            },
            "status": {
                "id": 1,
                "name": "New"
            },
            "priority": {
                "id": 4,
                "name": "\u041d\u043e\u0440\u043c\u0430\u043b\u044c\u043d\u044b\u0439"
            },
            "author": {
                "id": 4,
                "name": "A.  Haletsky"
            },
            "assigned_to": {
                "id": 428,
                "name": "A. Zharikov"
            },
            "subject": "\u041f\u0435\u0440\u0435\u0440\u0430\u0431\u043e\u0442\u043a\u0430 \u0440\u0435\u0434\u0430\u043a\u0442\u043e\u0440\u0430 \u0441\u043e\u043e\u0431\u0449\u0435\u043d\u0438\u0439.",
            "description": "\u0414\u0435\u043b\u0430\u0435\u043c \u043e\u0431\u0449\u0438\u0439 \u043a\u043e\u043c\u043f\u043e\u043d\u0435\u043d\u0442 \u0434\u043b\u044f \u0440\u0435\u0434\u0430\u043a\u0442\u0438\u0440\u043e\u0432\u0430\u043d\u0438\u044f \u0441\u043e\u043e\u0431\u0449\u0435\u043d\u0438\u0439 \u043a\u043e\u0442\u043e\u0440\u044b\u0439 \u0431\u0443\u0434\u0435\u043c \u0438\u0441\u043f\u043e\u043b\u044c\u0437\u043e\u0432\u0430\u0442\u044c \u0432\u0435\u0437\u0434\u0435 \u0433\u0434\u0435 \u043f\u0438\u0448\u0435\u043c \u043f\u0438\u0441\u044c\u043c\u0430.\r\n\r\n\u0412 \u0447\u0430\u0441\u0442\u043d\u043e\u0441\u0442\u0438:\r\n* \u0428\u0430\u0431\u043b\u043e\u043d\u044b\r\n* \u0426\u0435\u043f\u043e\u0447\u043a\u0438-\u0440\u0435\u0434\u0430\u043a\u0442\u0438\u0440\u043e\u0432\u0430\u043d\u0438\u0435 \u0441\u043e\u043e\u0431\u0449\u0435\u043d\u0438\u0439\r\n* \u0438 \u0442\u0434.\r\n\r\n\r\nh2. \u0411\u043b\u043e\u043a \"\u043d\u0430\u0441\u0442\u0440\u043e\u0439\u043a\u0438\" (\u0431\u0443\u0434\u0435\u0442 \u043e\u0442\u043b\u0438\u0447\u0430\u0442\u044c\u0441\u044f \u0432 \u0440\u0430\u0437\u043d\u044b \u0434\u0438\u0430\u043b\u043e\u0433\u0430\u0445).\r\n\r\nh3. \u0414\u043b\u044f \u0440\u0435\u0434\u0430\u043a\u0442\u0438\u0440\u043e\u0432\u0430\u043d\u0438\u044f \u0448\u0430\u0431\u043b\u043e\u043d\u043e\u0432:\r\n\r\n* \u041d\u0430\u0437\u0432\u0430\u043d\u0438\u0435\r\n* \u041e\u043f\u0438\u0441\u0430\u043d\u0438\u0435 (\u0434\u043e\u0431\u0430\u0432\u043b\u044f\u0435\u043c, \u043f\u043e\u043a\u0430 \u043d\u0438\u0433\u0434\u0435 \u043d\u0435 \u0432\u044b\u0432\u043e\u0434\u0438\u043c)\r\n* \u041f\u0443\u0431\u043b\u0438\u0447\u043d\u044b\u0439 (\u0434\u0430-\u043d\u0435\u0442)\r\n\r\nh2. \u0414\u043b\u044f \"\u0440\u0435\u0434\u0430\u043a\u0442\u0438\u0440\u0432\u043e\u0430\u043d\u0438\u044f \u0441\u043e\u043e\u0431\u0449\u0435\u043d\u0438\u044f \u0432 \u0446\u0435\u043f\u043e\u0447\u043a\u0430\u0445\"\r\n\r\n* \u0420\u0430\u0441\u043f\u0438\u0441\u0430\u043d\u0438\u0435\r\n** \u041e\u0442\u043f\u0440\u0430\u0432\u043a\u0430 \u043f\u043e \u0432\u0440\u0435\u043c\u0435\u043d\u0438 \u0438\u043b\u0438 \u0441 \u0437\u0430\u0434\u0435\u0440\u0436\u043a\u043e\u0439 (\u0432 \u0437\u0430\u0432\u0438\u0441\u0438\u043c\u043e\u0441\u0442\u0438 \u043e\u0442 \u0432\u044b\u0431\u043e\u0440\u0430 \u0432\u0430\u0440\u0438\u0430\u043d\u0442\u0430 \u043f\u043e\u043a\u0430\u0437\u044b\u0432\u0430\u0442\u044c \u0440\u0430\u0437\u043d\u044b\u0435 \u043d\u0430\u0431\u043e\u0440\u044b \u043f\u043e\u043b\u0435\u0439)\r\n** \u0422\u043e\u0447\u043d\u043e\u0435 \u0432\u0440\u0435\u043c\u044f\r\n*** \u0427\u0435\u0440\u0435\u0437 \u041d \u0434\u043d\u0435\u0439\r\n*** \u0412 \u044d\u0442\u043e \u0432\u0440\u0435\u043c\u044f\r\n** \u0417\u0430\u0434\u0435\u0440\u0436\u043a\u0430 \u043f\u0435\u0440\u0435\u0434 \u043e\u0442\u043f\u0440\u0430\u0432\u043a\u043e\u0439\r\n*** \u0427\u0435\u0440\u0435\u0437 \u041d \u0434\u043d\u0435\u0439, \u0447\u0430\u0441\u043e\u0432, \u043c\u0438\u043d\u0443\u0442\r\n\r\nh2. \u0411\u043b\u043e\u043a \"\u0440\u0435\u0434\u0430\u043a\u0442\u043e\u0440\".\r\n\r\n\u041e\u0441\u043d\u043e\u0432\u043d\u0430\u044f \u0447\u0430\u0441\u0442\u044c:\r\n* \u0417\u0430\u0433\u043e\u043b\u043e\u0432\u043e\u043a(\u0438) (\u0442\u0443\u0442 \u0445\u043e\u0447\u0443 \u0447\u0442\u043e\u0431\u044b \u0431\u044b\u043b\u0430 \u043e\u043f\u0446\u0438\u044f \u0434\u043e\u0431\u0430\u0432\u043b\u044f\u0442\u044c \u043d\u0435\u0441\u043a\u043e\u043b\u044c\u043a\u043e \u0437\u0430\u0433\u043e\u043b\u043e\u0432\u043a\u043e\u0432, \u0432\u043e\u0437\u043c\u043e\u0436\u043d\u043e \u0432 \u043f\u043e\u043f\u0430\u043f\u0435 \u043e\u0442\u0434\u0435\u043b\u044c\u043d\u043e\u043c \u0438 \u043f\u043e\u043a\u0430\u0437\u044b\u0432\u0430\u0442\u044c \u0441\u043a\u043e\u043b\u044c\u043a\u043e \u0438\u0445 \u0432\u0441\u0435\u0433\u043e)\r\n* \u0420\u0435\u0434\u0430\u043a\u0442\u043e\u0440\r\n* \u0410\u0442\u0442\u0430\u0447\u0438\r\n* \u041f\u0440\u0435\u0432\u044c\u044e (\u043d\u0435 \u043f\u043e\u043a\u0430\u0437\u044b\u0432\u0430\u0442\u044c \u043e\u043d\u043b\u0430\u0439\u043d, \u0441\u043f\u0440\u044f\u0442\u0430\u0442\u044c\u043d\u0430 \"\u043f\u043e \u0437\u0430\u043f\u0440\u043e\u0441\u0443\" \u0432\u0435\u0440\u043e\u044f\u0442\u043d\u043e \u0432 \u043f\u043e\u043f\u0430\u043f\r\n\r\n\u0414\u043e\u043f. \u043a\u043e\u043b\u043e\u043d\u043a\u0430 (\u0432\u043d\u0443\u0442\u0440\u0438 \u0434\u0432\u0435):\r\n* \u041c\u0430\u043a\u0440\u043e\u0441\u044b\r\n* \u0424\u0440\u0430\u0433\u043c\u0435\u043d\u0442\u044b\r\n\r\n+ \u0441\u0434\u0435\u043b\u0430\u0442\u044c \u0438\u0445 \u0433\u0440\u0443\u043f\u043f\u0438\u0440\u043e\u0432\u043a\u0443 \u0438 \"\u0440\u0430\u0437\u0432\u043e\u0440\u0430\u0447\u0438\u0432\u0430\u043d\u0438\u0435\"",
            "start_date": "2022-03-25",
            "done_ratio": 0,
            "estimated_hours": 30.0,
            "created_on": "2022-03-25T08:01:02Z",
            "updated_on": "2022-03-25T08:01:02Z"
        },
        {
            "id": 30178,
            "project": {
                "id": 491,
                "name": "Mail Trade CRM v.2"
            },
            "tracker": {
                "id": 1,
                "name": "Bug"
            },
            "status": {
                "id": 1,
                "name": "New"
            },
            "priority": {
                "id": 5,
                "name": "\u0412\u044b\u0441\u043e\u043a\u0438\u0439"
            },
            "author": {
                "id": 433,
                "name": "A. Stratan"
            },
            "assigned_to": {
                "id": 428,
                "name": "A. Zharikov"
            },
            "fixed_version": {
                "id": 1788,
                "name": "Front CRM"
            },
            "subject": "Chains: \u041d\u0435 \u0437\u0430\u043a\u0440\u044b\u0432\u0430\u0435\u0442\u0441\u044f \u043c\u0435\u043d\u044e \u0440\u0435\u0434\u0430\u043a\u0442\u0438\u0440\u043e\u0432\u0430\u043d\u0438\u044f",
            "description": "\u041f\u043e\u0441\u043b\u0435 \u0442\u043e\u0433\u043e \u043a\u0430\u043a \u043c\u044b \u043f\u0440\u043e\u0432\u0435\u043b\u0438 \u0440\u0435\u0434\u0430\u043a\u0442\u0438\u0440\u043e\u0432\u0430\u043d\u0438\u0435 \u0438\u043b\u0438 \u0441\u043e\u0437\u0434\u0430\u043d\u0438\u0435 \u0446\u0435\u043f\u043e\u0447\u043a\u0438, \u0432\u0435\u0441\u0438\u0442 \u043c\u0435\u043d\u044e \"\u0440\u0435\u0434\u0430\u043a\u0442\u0438\u0440\u043e\u0432\u0430\u043d\u0438\u044f\"\r\n\r\n*\u0428\u0430\u0433\u0438 \u0432\u043e\u0441\u043f\u0440\u043e\u0438\u0437\u0432\u0435\u0434\u0435\u043d\u0438\u044f:* (login admin)\r\n\r\n# http://135.181.90.157/letter_fragments_and_templates?direction&page=1&per_page=50&sort\r\n# \u0426\u0435\u043f\u043e\u0447\u043a\u0438/\u0440\u0435\u0434\u0430\u043a\u0442\u0438\u0440\u043e\u0432\u0430\u0442\u044c\r\n# \u041e\u0442\u043a\u0440\u044b\u0432\u0430\u0435\u0442\u0441\u044f \u043c\u0435\u043d\u044e\r\n# \u0414\u0435\u043b\u0430\u0435\u043c \u043f\u0440\u0430\u0432\u043a\u0438 \u0438\u043b\u0438 \u0441\u043c\u043e\u0442\u0440\u0438\u043c \u0438\u043d\u0444\u043e\u0440\u043c\u0430\u0446\u0438\u044e\r\n# \u0437\u0430\u043a\u0440\u044b\u0432\u0430\u0435\u043c \u043c\u043e\u0434\u0430\u043b\u043a\u0443\r\n\r\n*\u0420\u0435\u0437\u0443\u043b\u044c\u0442\u0430\u0442:*\r\n\u041f\u043e\u0441\u043b\u0435 \u043f\u0440\u043e\u0432\u0435\u0434\u0435\u043d\u0438\u044f \u0440\u0435\u0434\u0430\u043a\u0442\u0438\u0440\u043e\u0432\u0430\u043d\u0438\u044f. \u043c\u0435\u043d\u044e \u043d\u0435 \u0437\u0430\u043a\u0440\u044b\u0432\u0430\u0435\u0442\u0441\u044f \u0441\u0430\u043c\u043e\u0441\u0442\u043e\u044f\u0442\u0435\u043b\u044c\u043d\u043e, \u0442\u043e\u043b\u044c\u043a\u043e \u0432\u0440\u0443\u0447\u043d\u0443\u044e",
            "start_date": "2022-03-24",
            "done_ratio": 0,
            "estimated_hours": 0.2,
            "created_on": "2022-03-24T16:26:13Z",
            "updated_on": "2022-03-24T16:26:13Z"
        },
        {
            "id": 30174,
            "project": {
                "id": 491,
                "name": "Mail Trade CRM v.2"
            },
            "tracker": {
                "id": 1,
                "name": "Bug"
            },
            "status": {
                "id": 1,
                "name": "New"
            },
            "priority": {
                "id": 5,
                "name": "\u0412\u044b\u0441\u043e\u043a\u0438\u0439"
            },
            "author": {
                "id": 433,
                "name": "A. Stratan"
            },
            "assigned_to": {
                "id": 428,
                "name": "A. Zharikov"
            },
            "fixed_version": {
                "id": 1788,
                "name": "Front CRM"
            },
            "subject": "Chains: \u0411\u0435\u043b\u044b\u0439 \u044d\u043a\u0440\u0430\u043d \u0432 \u0446\u0435\u043f\u043e\u0447\u043a\u0430\u0445 \u043f\u043e\u0441\u043b\u0435 \u043d\u0430\u0436\u0430\u0442\u0438\u044f \u043d\u0430 \u0441\u0442\u0440\u0435\u043b\u043e\u0447\u043a\u0443",
            "description": "\u041f\u0440\u0438 \u043d\u0430\u0436\u0430\u0442\u0438\u0438 \u043d\u0430 \u0441\u0442\u0440\u0435\u043b\u043a\u0443 \u0441\u043e\u0440\u0442\u0438\u0440\u043e\u0432\u043a\u0438 \u0441\u0432\u0435\u0440\u0445\u0443 \u0432\u043d\u0438\u0437 \u0438\u043b\u0438 \u0441\u043d\u0438\u0437\u0443 \u0432\u0432\u0435\u0440\u0445\r\n\r\n*\u0428\u0430\u0433\u0438 \u0432\u043e\u0441\u043f\u0440\u043e\u0438\u0437\u0432\u0435\u0434\u0435\u043d\u0438\u044f:* (login admin)\r\n\r\n# http://135.181.90.157/letter_fragments_and_templates?direction=asc&page=1&per_page=15&sort=t.name\r\n# \u0426\u0435\u043f\u043e\u0447\u043a\u0438/\u041d\u0430\u0436\u0430\u0442\u044c \u043d\u0430 \u0441\u0442\u0440\u0435\u043b\u043e\u0447\u043a\u0443 \u0441\u043e\u0440\u0442\u0438\u0440\u043e\u0432\u043a\u0438\r\n\r\n*\u0420\u0435\u0437\u0443\u043b\u044c\u0442\u0430\u0442:*\r\n\u0412\u0438\u0441\u043d\u0435\u0442 \u0431\u0435\u043b\u044b\u0439 \u044d\u043a\u0440\u0430\u043d, \u0441\u0442\u0440\u0430\u043d\u0438\u0446\u0430 \u0432\u043e\u0441\u0441\u0442\u0430\u043d\u0430\u0432\u043b\u0438\u0432\u0430\u0435\u0442\u0441\u044f \u043f\u043e\u0441\u043b\u0435 \u043e\u0431\u043d\u043e\u0432\u043b\u0435\u043d\u0438\u044f",
            "start_date": "2022-03-24",
            "done_ratio": 0,
            "estimated_hours": 0.2,
            "created_on": "2022-03-24T12:24:58Z",
            "updated_on": "2022-03-24T15:14:18Z"
        },
        {
            "id": 30173,
            "project": {
                "id": 491,
                "name": "Mail Trade CRM v.2"
            },
            "tracker": {
                "id": 1,
                "name": "Bug"
            },
            "status": {
                "id": 1,
                "name": "New"
            },
            "priority": {
                "id": 5,
                "name": "\u0412\u044b\u0441\u043e\u043a\u0438\u0439"
            },
            "author": {
                "id": 433,
                "name": "A. Stratan"
            },
            "assigned_to": {
                "id": 428,
                "name": "A. Zharikov"
            },
            "fixed_version": {
                "id": 1788,
                "name": "Front CRM"
            },
            "subject": "Chains: \u041d\u0435 \u0443\u0434\u0430\u043b\u044f\u0435\u0442\u0441\u044f \u0441\u043e\u0437\u0434\u0430\u043d\u043d\u0430\u044f \u0446\u0435\u043f\u043e\u0447\u043a\u0430",
            "description": "\u041d\u0435 \u0443\u0434\u0430\u043b\u044f\u0435\u0442\u0441\u044f \u0432\u043d\u043e\u0432\u044c \u0441\u043e\u0437\u0434\u0430\u043d\u043d\u0430\u044f \u0446\u0435\u043f\u043e\u0447\u043a\u0430, \u043f\u0438\u0448\u0435\u0442 \u0447\u0442\u043e \u0446\u0435\u043f\u043e\u0447\u043a\u0430 \u0443\u0441\u043f\u0435\u0448\u043d\u043e \u0443\u0434\u0430\u043b\u0435\u043d\u0430\r\n\r\n*\u0428\u0430\u0433\u0438 \u0432\u043e\u0441\u043f\u0440\u043e\u0438\u0437\u0432\u0435\u0434\u0435\u043d\u0438\u044f:* (login admin)\r\n\r\n# http://135.181.90.157/letter_fragments_and_templates?direction&page=1&per_page=15&sort\r\n# \u0423\u0434\u0430\u043b\u0438\u0442\u044c \u043f\u043e\u0441\u043b\u0435\u0434\u043d\u044e\u044e \u0441\u043e\u0437\u0434\u0430\u043d\u043d\u0443\u044e \u0446\u0435\u043f\u043e\u0447\u043a\u0443\r\n\r\n*\u0420\u0435\u0437\u0443\u043b\u044c\u0442\u0430\u0442:*\r\n\u041f\u043e \u0444\u0430\u043a\u0442\u0443 3 \u043f\u043e\u0441\u043b\u0435\u0434\u043d\u0438\u0435 \u0446\u0435\u043f\u043e\u0447\u043a\u0438 \u043a\u043e\u0442\u043e\u0440\u044b\u0435 \u0431\u044b\u043b\u0438 \u0441\u043e\u0437\u0434\u0430\u043d\u044b, \u043d\u0435 \u0443\u0434\u0430\u043b\u044f\u044e\u0442\u0441\u044f\r\n ",
            "start_date": "2022-03-24",
            "done_ratio": 0,
            "estimated_hours": 0.3,
            "created_on": "2022-03-24T11:15:10Z",
            "updated_on": "2022-03-24T12:35:30Z"
        },
        {
            "id": 30172,
            "project": {
                "id": 491,
                "name": "Mail Trade CRM v.2"
            },
            "tracker": {
                "id": 6,
                "name": "Task"
            },
            "status": {
                "id": 2,
                "name": "In Progress"
            },
            "priority": {
                "id": 5,
                "name": "\u0412\u044b\u0441\u043e\u043a\u0438\u0439"
            },
            "author": {
                "id": 433,
                "name": "A. Stratan"
            },
            "assigned_to": {
                "id": 428,
                "name": "A. Zharikov"
            },
            "fixed_version": {
                "id": 1788,
                "name": "Front CRM"
            },
            "subject": "Chains: \u0414\u043e\u0431\u0430\u0432\u0438\u0442\u044c \u0432 \u0442\u0430\u0431\u043b\u0438\u0446\u0443 \"\u0446\u0435\u043f\u043e\u0447\u043a\u0438\" \u043a\u043e\u043b\u0438\u0447\u0435\u0441\u0442\u0432\u043e \u0441\u043e\u043e\u0431\u0449\u0435\u043d\u0438\u0439",
            "description": "* \u0412 \u0442\u0430\u0431\u043b\u0438\u0446\u0443 \"\u0446\u0435\u043f\u043e\u0447\u043a\u0438\" \u0434\u043e\u0431\u0430\u0432\u0438\u0442\u044c \u0441\u0442\u043e\u043b\u0431\u0438\u043a \u0441 \u043e\u0442\u043e\u0431\u0440\u0430\u0436\u0435\u043d\u0438\u0435\u043c \u043a\u043e\u043b\u0438\u0447\u0435\u0441\u0442\u0432\u0430 \u0441\u043e\u043e\u0431\u0449\u0435\u043d\u0438\u0439 \u0432 \u043a\u0430\u0436\u0434\u043e\u0439 \u0446\u0435\u043f\u043e\u0447\u043a\u0435",
            "start_date": "2022-03-24",
            "done_ratio": 30,
            "estimated_hours": 0.2,
            "created_on": "2022-03-24T09:40:04Z",
            "updated_on": "2022-03-25T16:12:43Z"
        },
        {
            "id": 30171,
            "project": {
                "id": 491,
                "name": "Mail Trade CRM v.2"
            },
            "tracker": {
                "id": 5,
                "name": "Feature"
            },
            "status": {
                "id": 1,
                "name": "New"
            },
            "priority": {
                "id": 4,
                "name": "\u041d\u043e\u0440\u043c\u0430\u043b\u044c\u043d\u044b\u0439"
            },
            "author": {
                "id": 433,
                "name": "A. Stratan"
            },
            "assigned_to": {
                "id": 428,
                "name": "A. Zharikov"
            },
            "subject": "Chains: \u041b\u0438\u0448\u043d\u044f\u044f \u0431\u0443\u043a\u0432\u0430 \u0432 \u0442\u0435\u043a\u0441\u0442\u0435 \u0432 \u043c\u043e\u0434\u0430\u043b\u043a\u0435 \"\u0446\u0435\u043f\u043e\u043a\u0438\"",
            "description": "\u0412\u0440\u0435\u043c\u044f \u0441 \u043a\u043e\u0442\u043e\u0440\u043e\u0433\u043e \u0437\u0430\u043a\u0430\u043d\u0447\u0438\u0432\u0430\u0435\u0442\u0441\u044f \u0440\u0430\u0441\u0441\u044b\u043b\u043a\u0430 \u043f\u0438\u0441\u0435\u043c (\u0432) \u0432 \u0434\u043d\u0435 \u0440\u0430\u0441\u0441\u044b\u043b\u043a\u0438\r\n\r\n*\u0428\u0430\u0433\u0438:*\r\n\r\n# http://135.181.90.157/letter_fragments_and_templates\r\n# \u0421\u043e\u0437\u0434\u0430\u0442\u044c \u0446\u0435\u043f\u043e\u0447\u043a\u0443\r\n# \u0414\u043e\u0431\u0430\u0432\u0438\u0442\u044c \u0441\u043e\u043e\u0431\u0449\u0435\u043d\u0438\u0435\r\n# \u0418\u0441\u043f\u0440\u0430\u0432\u0438\u0442\u044c \u043e\u0448\u0438\u0431\u043a\u0443 \u0432 \u0442\u0435\u043a\u0441\u0442\u0435",
            "start_date": "2022-03-24",
            "done_ratio": 0,
            "estimated_hours": 0.15,
            "created_on": "2022-03-24T08:06:00Z",
            "updated_on": "2022-03-24T08:06:22Z"
        },
        {
            "id": 30170,
            "project": {
                "id": 491,
                "name": "Mail Trade CRM v.2"
            },
            "tracker": {
                "id": 1,
                "name": "Bug"
            },
            "status": {
                "id": 1,
                "name": "New"
            },
            "priority": {
                "id": 5,
                "name": "\u0412\u044b\u0441\u043e\u043a\u0438\u0439"
            },
            "author": {
                "id": 433,
                "name": "A. Stratan"
            },
            "assigned_to": {
                "id": 428,
                "name": "A. Zharikov"
            },
            "subject": "\u041a\u0440\u0430\u0448 \u043f\u0440\u0438 \u043f\u043e\u043f\u044b\u0442\u043a\u0435 \u0437\u0430\u0434\u0430\u0442\u044c \u0444\u0438\u043b\u044c\u0442\u0440 \u0432 \"\u043b\u0438\u0434\u0430\u0445\"",
            "description": "\u041f\u0440\u0438 \u043f\u043e\u043f\u044b\u0442\u043a\u0435 \u0437\u0430\u0434\u0430\u0442\u044c \u0444\u0438\u043b\u044c\u0442\u0440 \u0432 \"\u043b\u0438\u0434\u0430\u0445\"  \u044d\u043a\u0440\u0430\u043d \u0441\u0442\u0430\u043d\u043e\u0432\u0438\u0442\u0441\u044f \u0431\u0435\u043b\u0435\u0441\u044b\u0439\r\n\r\n*\u0428\u0430\u0433\u0438 \u0432\u043e\u0441\u043f\u0440\u043e\u0438\u0437\u0432\u0435\u0434\u0435\u043d\u0438\u044f:* (login admin)\r\n\r\n# http://135.181.90.157/project/8/leads_manage\r\n# \u041e\u0442\u043a\u0440\u044b\u0442\u044c \u043f\u0440\u043e\u0435\u043a\u0442\u044b\r\n# \u0420\u0430\u0431\u043e\u0442\u0430 \u0441 \u043b\u0438\u0434\u0430\u043c\u0438\r\n\r\n*\u0420\u0435\u0437\u0443\u043b\u044c\u0442\u0430\u0442:*\r\n\u0412 \u043b\u044e\u0431\u043e\u043c \u043f\u0440\u043e\u0435\u043a\u0442\u0435 \u043e\u0442\u043a\u0440\u044b\u0432\u0430\u0435\u043c \"\u0440\u0430\u0431\u043e\u0442\u0443 \u0441 \u043b\u0438\u0434\u0430\u043c\u0438\", \u0437\u0430\u0434\u0430\u0451\u043c \u043b\u044e\u0431\u043e\u0439 \u0444\u0438\u043b\u044c\u0442\u0440, \u044d\u043a\u0440\u0430\u043d \u0441\u0442\u0430\u043d\u043e\u0432\u0438\u0442\u0441\u044f \u0431\u0435\u043b\u0435\u0441\u044b\u0439 \u0438 \u0432\u0438\u0441\u043d\u0435\u0442, \u043e\u0431\u043d\u043e\u0432\u043b\u0435\u043d\u0438\u0435 \u0432\u043e\u0441\u0441\u0442\u0430\u043d\u0430\u0432\u043b\u0438\u0432\u0430\u0435\u0442 \u0441\u0442\u0440\u0430\u043d\u0438\u0446\u0443",
            "start_date": "2022-03-23",
            "done_ratio": 0,
            "estimated_hours": 0.3,
            "created_on": "2022-03-23T15:04:40Z",
            "updated_on": "2022-03-23T15:04:40Z"
        },
        {
            "id": 30167,
            "project": {
                "id": 491,
                "name": "Mail Trade CRM v.2"
            },
            "tracker": {
                "id": 1,
                "name": "Bug"
            },
            "status": {
                "id": 1,
                "name": "New"
            },
            "priority": {
                "id": 4,
                "name": "\u041d\u043e\u0440\u043c\u0430\u043b\u044c\u043d\u044b\u0439"
            },
            "author": {
                "id": 433,
                "name": "A. Stratan"
            },
            "assigned_to": {
                "id": 428,
                "name": "A. Zharikov"
            },
            "fixed_version": {
                "id": 1788,
                "name": "Front CRM"
            },
            "parent": {
                "id": 30079
            },
            "subject": "Chains: \u041d\u0435 \u043c\u0435\u043d\u044f\u0435\u0442\u0441\u044f \u043a\u043e\u043b\u0438\u0447\u0435\u0441\u0442\u0432\u043e \u0441\u0442\u0440\u043e\u043a \u0432 \u043f\u0430\u0433\u0438\u043d\u0430\u0446\u0438\u0438 \u0442\u0430\u0431\u043b\u0438\u0446\u044b",
            "description": "\u041f\u0440\u0438 \u043b\u044e\u0431\u043e\u043c \u0438\u0437\u043c\u0435\u043d\u0435\u043d\u0438\u0438 \u043a\u043e\u043b\u0438\u0447\u0435\u0441\u0442\u0432\u0430 \u0441\u0442\u0440\u043e\u043a \u043d\u0430 \u0441\u0442\u0440\u0430\u043d\u0438\u0446\u0435 \"\u0446\u0435\u043f\u043e\u0447\u043a\u0438\". \u043f\u0430\u0433\u0438\u043d\u0430\u0446\u0438\u044f \u0442\u0430\u0431\u043b\u0438\u0446\u044b \u043e\u0441\u0442\u0430\u0451\u0442\u0441\u044f 0-0 \u0438\u0437 0\r\n\r\n*\u0428\u0430\u0433\u0438 \u0432\u043e\u0441\u043f\u0440\u043e\u0438\u0437\u0432\u0435\u0434\u0435\u043d\u0438\u044f:* (login admin)\r\n\r\n# http://135.181.90.157/letter_fragments_and_templates?direction&page=1&per_page=25&sort\r\n# \u0412\u044b\u0431\u0440\u0430\u0442\u044c \u0441\u043e\u0440\u0442\u0438\u0440\u043e\u0432\u043a\u0443 \u0441\u0442\u0440\u043e\u043a (5,10,25,50 \u0438 \u0442.\u0434.)\r\n\r\n*\u0420\u0435\u0437\u0443\u043b\u044c\u0442\u0430\u0442:*\r\n\u041f\u0440\u0438 \u0432\u044b\u0431\u043e\u0440\u0435 \u043a\u043e\u043b\u0438\u0447\u0435\u0441\u0442\u0432\u0430 \u0441\u0442\u0440\u043e\u043a. \u043f\u0430\u0433\u0438\u043d\u0430\u0446\u0438\u044f \u0442\u0430\u0431\u043b\u0438\u0446\u044b \u043e\u0441\u0442\u0430\u0451\u0442\u0441\u044f \u043d\u0435\u0438\u0437\u043c\u0435\u043d\u043d\u043e\u0439 \u0438 \u043f\u043e\u043a\u0430\u0437\u044b\u0432\u0430\u0435\u0442 0-0 \u0438\u0437 0 ",
            "start_date": "2022-03-23",
            "done_ratio": 0,
            "created_on": "2022-03-23T09:54:58Z",
            "updated_on": "2022-03-24T07:46:02Z"
        },
        {
            "id": 30165,
            "project": {
                "id": 491,
                "name": "Mail Trade CRM v.2"
            },
            "tracker": {
                "id": 1,
                "name": "Bug"
            },
            "status": {
                "id": 1,
                "name": "New"
            },
            "priority": {
                "id": 5,
                "name": "\u0412\u044b\u0441\u043e\u043a\u0438\u0439"
            },
            "author": {
                "id": 433,
                "name": "A. Stratan"
            },
            "assigned_to": {
                "id": 428,
                "name": "A. Zharikov"
            },
            "fixed_version": {
                "id": 1788,
                "name": "Front CRM"
            },
            "subject": "Templaise: \u041f\u0440\u0438 \u043d\u0430\u0436\u0430\u0442\u0438\u0438 \u043d\u0430 \u0441\u0442\u0440\u0435\u043b\u043a\u0443 \u0441\u043e\u0440\u0442\u0438\u0440\u043e\u0432\u043a\u0438 \u043f\u0440\u043e\u043f\u0430\u0434\u0430\u044e\u0442 \u0432\u0441\u0435 \u0448\u0430\u0431\u043b\u043e\u043d\u044b",
            "description": "\u041f\u0440\u0438 \u043d\u0430\u0436\u0430\u0442\u0438\u0438 \u043d\u0430 \u0441\u0442\u0440\u0435\u043b\u043a\u0443 \u0441\u043e\u0440\u0442\u0438\u0440\u043e\u0432\u043a\u0438 \u043f\u0440\u043e\u043f\u0430\u0434\u0430\u044e\u0442 \u0432\u0441\u0435 \u0448\u0430\u0431\u043b\u043e\u043d\u044b\r\n\r\n*\u0428\u0430\u0433\u0438 \u0432\u043e\u0441\u043f\u0440\u043e\u0438\u0437\u0432\u0435\u0434\u0435\u043d\u0438\u044f:* (login admin)\r\n\r\n# http://135.181.90.157/\r\n# \u041a\u043b\u0438\u043a\u043d\u0443\u0442\u044c \u043d\u0430 \u0441\u0442\u0440\u0435\u043b\u043a\u0443 \u0441\u043e\u0440\u0442\u0438\u0440\u043e\u0432\u043a\u0438, \u0440\u044f\u0434\u043e\u043c \u0441\u043b\u043e\u0432\u043e \"\u0438\u043c\u044f\"\r\n\r\n*\u0420\u0435\u0437\u0443\u043b\u044c\u0442\u0430\u0442:*\r\n\u0421\u0442\u0440\u0435\u043b\u043a\u0430 \u043a\u0440\u0443\u0442\u0438\u0442\u0441\u044f, \u0432\u0441\u0435 \u0448\u0430\u0431\u043b\u043e\u043d\u044b \u043f\u0440\u043e\u043f\u0430\u0434\u0430\u044e\u0442, \u043f\u043e\u0441\u043b\u0435 \u043e\u0431\u043d\u043e\u0432\u043b\u0435\u043d\u0438\u044f \u0441\u0442\u0440\u0430\u043d\u0438\u0446\u044b \u0432\u0441\u0451 \u0432\u043e\u0441\u0442\u0430\u043d\u0430\u0432\u043b\u0438\u0432\u0430\u0435\u0442\u0441\u044f",
            "start_date": "2022-03-23",
            "done_ratio": 0,
            "created_on": "2022-03-23T09:09:08Z",
            "updated_on": "2022-03-24T15:24:41Z"
        },
        {
            "id": 30161,
            "project": {
                "id": 491,
                "name": "Mail Trade CRM v.2"
            },
            "tracker": {
                "id": 5,
                "name": "Feature"
            },
            "status": {
                "id": 1,
                "name": "New"
            },
            "priority": {
                "id": 4,
                "name": "\u041d\u043e\u0440\u043c\u0430\u043b\u044c\u043d\u044b\u0439"
            },
            "author": {
                "id": 433,
                "name": "A. Stratan"
            },
            "assigned_to": {
                "id": 428,
                "name": "A. Zharikov"
            },
            "subject": "\u041e\u0448\u0438\u0431\u043a\u0430 \u0432 \u0441\u043b\u043e\u0432\u0435 \"\u0442\u0440\u0435\u043a\u043d\u043e\u043c\u0435\u0440\"",
            "description": "\u0428\u0430\u0433\u0438: (login admin)\r\n\r\nhttp://135.181.90.157/project/6/leads_manage\r\n\u0417\u0430\u0439\u0442\u0438 \u0432 \u043f\u0440\u043e\u0435\u043a\u0442\r\n\u041e\u0442\u043a\u0440\u044b\u0442\u044c \"\u0443\u043f\u0440\u0430\u0432\u043b\u0435\u043d\u0438\u0435 \u0442\u0440\u0435\u043a\u043d\u043e\u043c\u0435\u0440\u0430\u043c\u0438\"\r\n\r\n\u0420\u0435\u0437\u0443\u043b\u044c\u0442\u0430\u0442:\r\n\u041f\u0430\u043a\u0435\u0442\u043d\u0430\u044f \u0437\u0430\u043b\u0438\u0432\u043a\u0430 \u0432 \u0441\u043b\u043e\u0432\u0435 \u0422\u0440\u0435\u043a\u043d\u043e\u043c\u0435\u0440 \u043d\u0435 \u0445\u0432\u0430\u0442\u0430\u0435\u0442 \u0431\u0443\u043a\u0432\u044b \u043a",
            "start_date": "2022-03-22",
            "done_ratio": 0,
            "created_on": "2022-03-22T09:14:25Z",
            "updated_on": "2022-03-22T09:14:25Z"
        },
        {
            "id": 30155,
            "project": {
                "id": 491,
                "name": "Mail Trade CRM v.2"
            },
            "tracker": {
                "id": 1,
                "name": "Bug"
            },
            "status": {
                "id": 1,
                "name": "New"
            },
            "priority": {
                "id": 5,
                "name": "\u0412\u044b\u0441\u043e\u043a\u0438\u0439"
            },
            "author": {
                "id": 433,
                "name": "A. Stratan"
            },
            "assigned_to": {
                "id": 428,
                "name": "A. Zharikov"
            },
            "fixed_version": {
                "id": 1788,
                "name": "Front CRM"
            },
            "subject": "Chains: \u041f\u0440\u043e\u043f\u0430\u0434\u0430\u044e\u0442 \u0434\u043e\u0431\u0430\u0432\u043b\u0435\u043d\u043d\u044b\u0435 \u0430\u0442\u0442\u0430\u0447\u0438 \u0432 \"\u0446\u0435\u043f\u043e\u0447\u043a\u0430\u0445\"",
            "description": "\u041f\u0440\u0438 \u0440\u0435\u0434\u0430\u043a\u0442\u0438\u0440\u043e\u0432\u0430\u043d\u0438\u0438 \u0446\u0435\u043f\u043e\u0447\u043a\u0438, \u043f\u0440\u043e\u043f\u0430\u0434\u0430\u0435\u0442 \u0437\u043d\u0430\u0447\u043e\u043a \u0441\u043a\u0440\u0435\u043f\u043a\u0438 (\u043e\u0431\u043e\u0437\u043d\u0430\u0447\u0430\u044e\u0449\u0438\u0439 \u0434\u043e\u0431\u0430\u0432\u043b\u0435\u043d\u043d\u044b\u0435 \u0430\u0442\u0442\u0430\u0447\u0438 \u0432 \u0441\u043e\u043e\u0431\u0449\u0435\u043d\u0438\u0438), \u043f\u0440\u0438 \u043d\u0430\u0436\u0430\u0442\u0438\u0438 \u043d\u0430 \u043a\u043d\u043e\u043f\u043a\u0443 \"\u0438\u0437\u043c\u0435\u043d\u0438\u0442\u044c\"\r\n\r\n*\u0428\u0430\u0433\u0443 \u0432\u043e\u0441\u043f\u0440\u043e\u0438\u0437\u0432\u0435\u0434\u0435\u043d\u0438\u044f:* (login admin)\r\n\r\n# \u041e\u0442\u043a\u0440\u044b\u0442\u044c \"\u0446\u0435\u043f\u043e\u0447\u043a\u0438\"\r\n# \u041d\u0430\u0436\u0430\u0442\u044c \u043a\u043d\u043e\u043f\u043a\u0443 \u0440\u0435\u0434\u0430\u043a\u0442\u0438\u0440\u043e\u0432\u0430\u0442\u044c\r\n# \u0414\u043e\u0431\u0430\u0432\u0438\u0442\u044c \u0441\u043e\u043e\u0431\u0449\u0435\u043d\u0438\u0435 \u0432 \u0446\u0435\u043f\u043e\u0447\u043a\u0443\r\n# \u0412\u0432\u0435\u0441\u0442\u0438 \u0432\u0430\u043b\u0438\u0434\u043d\u044b\u0435 \u0434\u0430\u043d\u043d\u044b\u0435/\u0434\u043e\u0431\u0430\u0432\u0438\u0442\u044c \u0444\u0430\u0439\u043b\r\n# \u043d\u0430\u0436\u0430\u0442\u044c \"\u0438\u0437\u043c\u0435\u043d\u0438\u0442\u044c\"\r\n\r\n*\u0420\u0435\u0437\u0443\u043b\u044c\u0442\u0430\u0442:*\r\n\u041f\u043e\u0441\u043b\u0435 \u043d\u0430\u0436\u0430\u0442\u044c\u044f \u043b\u044e\u0431\u043e\u0439 \u043a\u043d\u043e\u043f\u043a\u0438 \u043f\u0440\u043e\u043f\u0430\u0434\u0430\u0435\u0442 \u0437\u043d\u0430\u0447\u043e\u043a \"\u0441\u043a\u0440\u0435\u043f\u043a\u0430\", \u0441\u043e\u043e\u0442\u0432\u0435\u0442\u0441\u0442\u0432\u0435\u043d\u043d\u043e \u043f\u0440\u043e\u043f\u0430\u0434\u0430\u044e\u0442 \u0434\u043e\u0431\u0430\u0432\u043b\u0435\u043d\u043d\u044b\u0435 \u0430\u0442\u0442\u0430\u0447\u0438 \u0432 \u0433\u043e\u0442\u043e\u0432\u043e\u043c \u0441\u043e\u043e\u0431\u0449\u0435\u043d\u0438\u0438",
            "start_date": "2022-03-21",
            "done_ratio": 0,
            "created_on": "2022-03-21T13:58:41Z",
            "updated_on": "2022-03-23T08:44:37Z"
        },
        {
            "id": 30154,
            "project": {
                "id": 491,
                "name": "Mail Trade CRM v.2"
            },
            "tracker": {
                "id": 1,
                "name": "Bug"
            },
            "status": {
                "id": 2,
                "name": "In Progress"
            },
            "priority": {
                "id": 5,
                "name": "\u0412\u044b\u0441\u043e\u043a\u0438\u0439"
            },
            "author": {
                "id": 433,
                "name": "A. Stratan"
            },
            "assigned_to": {
                "id": 428,
                "name": "A. Zharikov"
            },
            "fixed_version": {
                "id": 1788,
                "name": "Front CRM"
            },
            "subject": "Chains: \u041f\u0440\u043e\u043f\u0430\u0434\u0430\u0435\u0442 \u0434\u043e\u0431\u0430\u0432\u043b\u0435\u043d\u043d\u043e\u0435 \u0441\u043e\u043e\u0431\u0449\u0435\u043d\u0438\u0435 \u0432 \"\u0446\u0435\u043f\u043e\u0447\u043a\u0430\u0445\"",
            "description": "\u041f\u0440\u0438 \u043f\u043e\u0432\u0442\u043e\u0440\u043d\u043e\u043c \u043d\u0430\u0436\u0430\u0442\u0438\u0438 \u043d\u0430 \u043a\u043d\u043e\u043f\u043a\u0443 \"\u0438\u0437\u043c\u0435\u043d\u0438\u0442\u044c\" \u043f\u0440\u043e\u043f\u0430\u0434\u0430\u0435\u0442 \u0440\u0430\u043d\u0435\u0435 \u0434\u043e\u0431\u0430\u0432\u043b\u0435\u043d\u043d\u043e\u0435 \u0441\u043e\u043e\u0431\u0449\u0435\u043d\u0438\u0435\r\n\r\n*\u0428\u0430\u0433\u0438 \u0432\u043e\u0441\u043f\u0440\u043e\u0438\u0437\u0432\u0435\u0434\u0435\u043d\u0438\u044f:* (login admin)\r\n\r\n# http://135.181.90.157/letter_fragments_and_templates\r\n# \u0426\u0435\u043f\u043e\u0447\u043a\u0438/\u0440\u0435\u0434\u0430\u043a\u0442\u0438\u0440\u043e\u0432\u0430\u0442\u044c\r\n# \u0412\u0432\u0435\u0441\u0442\u0438 \u0432\u0430\u043b\u0438\u0434\u043d\u044b\u0435 \u0434\u0430\u043d\u043d\u044b\u0435\r\n# \u0418\u0437\u043c\u0435\u043d\u0438\u0442\u044c\r\n# \u041e\u0431\u043d\u043e\u0432\u0438\u0442\u044c \u0441\u0442\u0440\u0430\u043d\u0438\u0446\u0443\r\n# \u041d\u0430\u0436\u0430\u0442\u044c \u0440\u0435\u0434\u0430\u043a\u0442\u0438\u0440\u043e\u0432\u0430\u0442\u044c/\u041a\u043b\u0438\u043a\u043d\u0443\u0442\u044c \u043a\u043d\u043e\u043f\u043a\u0443 \u0438\u0437\u043c\u0435\u043d\u0438\u0442\u044c\r\n\r\n*\u0420\u0435\u0437\u0443\u043b\u044c\u0442\u0430\u0442:*\r\n\u041f\u043e\u0441\u043b\u0435 \u043f\u043e\u0432\u0442\u043e\u0440\u043d\u043e\u0433\u043e \u043d\u0430\u0436\u0430\u0442\u0438\u044f \u043d\u0430 \u043a\u043d\u043e\u043f\u043a\u0443 \"\u0438\u0437\u043c\u0435\u043d\u0438\u0442\u044c\" \u043f\u0440\u043e\u043f\u0430\u0434\u0430\u0435\u0442 \u0434\u043e\u0431\u0430\u0432\u043b\u0435\u043d\u043d\u043e\u0435 \u0440\u0430\u043d\u0435\u0435 \u0441\u043e\u043e\u0431\u0449\u0435\u043d\u0438\u0435",
            "start_date": "2022-03-21",
            "done_ratio": 0,
            "created_on": "2022-03-21T12:36:40Z",
            "updated_on": "2022-03-23T08:41:51Z"
        },
        {
            "id": 30144,
            "project": {
                "id": 503,
                "name": "\u041a\u0440\u0438\u043f\u0442\u0430"
            },
            "tracker": {
                "id": 5,
                "name": "Feature"
            },
            "status": {
                "id": 1,
                "name": "New"
            },
            "priority": {
                "id": 4,
                "name": "\u041d\u043e\u0440\u043c\u0430\u043b\u044c\u043d\u044b\u0439"
            },
            "author": {
                "id": 4,
                "name": "A.  Haletsky"
            },
            "assigned_to": {
                "id": 428,
                "name": "A. Zharikov"
            },
            "fixed_version": {
                "id": 1826,
                "name": "3"
            },
            "parent": {
                "id": 30085
            },
            "subject": "\u041f\u043e\u043f\u0430\u043f \u043e\u0431\u044a\u0435\u043a\u0442\u0430 \u043d\u0430 \u043a\u0430\u0440\u0442\u0435",
            "description": "\u041f\u0435\u0440\u0435\u0440\u0438\u0441\u043e\u0432\u0430\u0442\u044c \u0438\u043a\u043e\u043d\u043a\u0438 \u0434\u0435\u0439\u0441\u0442\u0432\u0438\u0439.\r\n\u041e\u0441\u0442\u0430\u0432\u0438\u0442\u044c:\r\n* \u041f\u043e\u0434\u0435\u043b\u0438\u0442\u044c\u0441\u044f (\u0444\u0431-\u0442\u0432\u0438\u0442\u0442\u0435\u0440-\u0441\u0441\u044b\u043b\u043a\u0430, \u0447\u0435\u0440\u0435\u0437 \u0434\u0438\u0430\u043b\u043e\u0433)\r\n* \u041f\u0440\u043e\u043b\u043e\u0436\u0438\u0442\u044c \u043c\u0430\u0440\u0448\u0440\u0443\u0442\r\n* \u0414\u043e\u0431\u0430\u0432\u0438\u0442\u044c \u0432 \u0438\u0437\u0431\u0440\u0430\u043d\u043d\u043e\u0435\r\n* \"Pin\"\r\n\r\n(\u0438\u0437\u043c\u0435\u0440\u0438\u0442\u044c \u0440\u0430\u0441\u0441\u0442\u043e\u044f\u043d\u0438\u0435 - \u0443\u0431\u0440\u0430\u0442\u044c)\r\n",
            "start_date": "2022-03-18",
            "done_ratio": 0,
            "estimated_hours": 6.0,
            "created_on": "2022-03-18T10:42:20Z",
            "updated_on": "2022-03-18T10:42:20Z"
        },
        {
            "id": 30122,
            "project": {
                "id": 491,
                "name": "Mail Trade CRM v.2"
            },
            "tracker": {
                "id": 1,
                "name": "Bug"
            },
            "status": {
                "id": 1,
                "name": "New"
            },
            "priority": {
                "id": 4,
                "name": "\u041d\u043e\u0440\u043c\u0430\u043b\u044c\u043d\u044b\u0439"
            },
            "author": {
                "id": 433,
                "name": "A. Stratan"
            },
            "assigned_to": {
                "id": 428,
                "name": "A. Zharikov"
            },
            "subject": "\u0412\u0438\u0441\u043d\u0435\u0442 \u043f\u043e\u043f\u0430\u043f Refresh",
            "description": "\u0428\u0430\u0433\u0438 \u0432\u043e\u0441\u043f\u0440\u043e\u0438\u0437\u0432\u0435\u0434\u0435\u043d\u0438\u044f: (\u043b\u043e\u0433\u0438\u043d user3/user3)\r\n\r\nhttp://135.181.90.157/project/1?direction=asc&page=1&per_page=15&sort=t.deadline\r\n\u0417\u0430\u043b\u043e\u0433\u0438\u043d\u0438\u0442\u044c\u0441\u044f user3/user3\r\n\u041e\u0442\u043a\u0440\u044b\u0442\u044c \u043f\u0440\u043e\u0435\u043a\u0442\u044b\r\n\u041e\u0442\u043a\u0440\u044b\u0442\u044c \u043b\u044e\u0431\u043e\u0439 \u043f\u0440\u043e\u0435\u043a\u0442\r\n\u041d\u0430\u0432\u043e\u0434\u0438\u043c \u043a\u0443\u0440\u0441\u043e\u0440 \u043d\u0430 \u043a\u043d\u043e\u043f\u043a\u0443 \"\u0441\u043e\u0437\u0434\u0430\u0442\u044c \u0437\u0430\u0434\u0430\u0447\u0443\" (\u043f\u043e\u044f\u0432\u043b\u044f\u0435\u0442\u0441\u044f \u043f\u043e\u043f\u0430\u043f \"refresh\")\r\n\u041d\u0430\u0436\u0430\u0442\u044c \u043a\u043d\u043e\u043f\u043a\u0443 \"\u0441\u043e\u0437\u0434\u0430\u0442\u044c \u0437\u0430\u0434\u0430\u0447\u0443\"\r\n\r\n\u0420\u0435\u0437\u0443\u043b\u044c\u0442\u0430\u0442\r\n\u041e\u0442\u043a\u0440\u044b\u0432\u0430\u0435\u0442\u0441\u044f \u043c\u043e\u0434\u0430\u043b\u043a\u0430, \u0438 \u043f\u043e\u043f\u0430\u043f refresh \u0432\u0438\u0441\u043d\u0435\u0442 \u0432 \u0432\u043e\u0437\u0434\u0443\u0445\u0435\r\n",
            "start_date": "2022-03-17",
            "done_ratio": 0,
            "created_on": "2022-03-17T13:39:31Z",
            "updated_on": "2022-03-18T13:55:33Z"
        },
        {
            "id": 30121,
            "project": {
                "id": 491,
                "name": "Mail Trade CRM v.2"
            },
            "tracker": {
                "id": 1,
                "name": "Bug"
            },
            "status": {
                "id": 1,
                "name": "New"
            },
            "priority": {
                "id": 4,
                "name": "\u041d\u043e\u0440\u043c\u0430\u043b\u044c\u043d\u044b\u0439"
            },
            "author": {
                "id": 433,
                "name": "A. Stratan"
            },
            "assigned_to": {
                "id": 428,
                "name": "A. Zharikov"
            },
            "subject": "\u041e\u0448\u0438\u0431\u043a\u0430 \u043f\u0440\u0438 \u043f\u0440\u043e\u0441\u043c\u043e\u0442\u0440\u0435 \u043b\u0438\u0434\u0430",
            "description": "*\u0428\u0430\u0433\u0438 \u0432\u043e\u0441\u043f\u0440\u043e\u0438\u0437\u0432\u0435\u0434\u0435\u043d\u0438\u044f:* (\u043b\u043e\u0433\u0438\u043d admin)\r\n\r\n# http://135.181.90.157/\r\n# \u0413\u043b\u0430\u0432\u043d\u0430\u044f \u0441\u0442\u0440\u0430\u043d\u0438\u0446\u0430/\u043d\u0438\u0436\u043d\u044f\u044f \u0442\u0430\u0431\u043b\u0438\u0446\u0430\r\n# \u041e\u0442\u043a\u0440\u044b\u0442\u044c \"\u043a\u0430\u0440\u0442\u0443 \u043a\u043b\u0438\u0435\u043d\u0442\u0430 \u0432 \u043e\u043a\u043d\u0435\"\r\n\r\n*\u0420\u0435\u0437\u0443\u043b\u044c\u0442\u0430\u0442:*\r\n\u0412 Console \u043e\u0448\u0438\u0431\u043a\u0430 404:\r\nxhr.js:210          GET http://135.181.153.78:8000/api/project-notes/project/NaN 404 (Not Found)",
            "start_date": "2022-03-17",
            "done_ratio": 0,
            "created_on": "2022-03-17T12:46:06Z",
            "updated_on": "2022-03-23T09:58:50Z"
        },
        {
            "id": 30120,
            "project": {
                "id": 491,
                "name": "Mail Trade CRM v.2"
            },
            "tracker": {
                "id": 1,
                "name": "Bug"
            },
            "status": {
                "id": 1,
                "name": "New"
            },
            "priority": {
                "id": 4,
                "name": "\u041d\u043e\u0440\u043c\u0430\u043b\u044c\u043d\u044b\u0439"
            },
            "author": {
                "id": 433,
                "name": "A. Stratan"
            },
            "assigned_to": {
                "id": 428,
                "name": "A. Zharikov"
            },
            "subject": "\u0412 \u0430\u0434\u043c\u0438\u043d \u043f\u0430\u043d\u0435\u043b\u0438 \u043e\u0448\u0438\u0431\u043a\u0430 \u0432 \"Track service\"",
            "description": "*\u0428\u0430\u0433\u0438 \u0432\u043e\u0441\u043f\u0440\u043e\u0438\u0437\u0432\u0435\u0434\u0435\u043d\u0438\u044f:* (\u043b\u043e\u0433\u0438\u043d admin)\r\n \r\n# http://135.181.153.78:8000/admin/tracks\r\n# \u0417\u0430\u0439\u0442\u0438 \u0432 admin \u043f\u0430\u043d\u0435\u043b\u044c\r\n# \u041e\u0442\u043a\u0440\u044b\u0442\u044c Track Service\r\n# \u041e\u0442\u043a\u0440\u044b\u0442\u044c \u0422\u0440\u0435\u043a\u0438\r\n\r\n*\u0420\u0435\u0437\u0443\u043b\u044c\u0442\u0430\u0442*\r\n* \u041e\u0442\u043a\u0440\u044b\u0432\u0430\u044e\u0442\u0441\u044f \u0442\u0440\u0435\u043a\u0438, \u0441\u0442\u0440\u0430\u043d\u0438\u0446\u0430 \u043e\u0431\u0440\u0435\u0437\u0430\u043d\u0430; \u0432 Console: \r\n* socket.io-client.js:2          GET http://135.181.153.78:3000/socket.io/?EIO=3&transport=polling&t=N-NZONK net::ERR_CONNECTION_REFUSED\r\n* :3000/socket.io/?EIO=3&transport=polling&t=N-NX1Bf:1          Failed to load resource: net::ERR_CONNECTION_REFUSED",
            "start_date": "2022-03-17",
            "done_ratio": 0,
            "created_on": "2022-03-17T11:14:30Z",
            "updated_on": "2022-03-18T13:57:43Z"
        },
        {
            "id": 30119,
            "project": {
                "id": 491,
                "name": "Mail Trade CRM v.2"
            },
            "tracker": {
                "id": 1,
                "name": "Bug"
            },
            "status": {
                "id": 1,
                "name": "New"
            },
            "priority": {
                "id": 4,
                "name": "\u041d\u043e\u0440\u043c\u0430\u043b\u044c\u043d\u044b\u0439"
            },
            "author": {
                "id": 433,
                "name": "A. Stratan"
            },
            "assigned_to": {
                "id": 428,
                "name": "A. Zharikov"
            },
            "subject": "\u041e\u0448\u0438\u0431\u043a\u0430 \u043f\u0440\u0438 \u043f\u0440\u043e\u0441\u043c\u043e\u0442\u0440\u0435 \u0437\u0430\u0434\u0430\u0447",
            "description": "*\u0428\u0430\u0433\u0438 \u0432\u043e\u0441\u043f\u0440\u043e\u0438\u0437\u0432\u0435\u0434\u0435\u043d\u0438\u044f:* (\u043b\u043e\u0433\u0438\u043d admin)\r\n\r\n# http://135.181.90.157/project/8 \u0438\u043b\u0438 http://135.181.90.157/project/8?direction&page=1&per_page=.%2410&sort\r\n# \u041e\u0442\u043a\u0440\u044b\u0442\u044c \u0433\u043b\u0430\u0432\u043d\u0430\u044f \u0441\u0442\u0440\u0430\u043d\u0438\u0446\u0430/\u043f\u0440\u043e\u0435\u043a\u0442\u044b\r\n# \u041e\u0442\u043a\u0440\u044b\u0442\u044c \u043b\u044e\u0431\u043e\u0439 \u043f\u0440\u043e\u0435\u043a\u0442/\u043f\u0440\u043e\u0441\u043c\u043e\u0442\u0440 \u0437\u0430\u0434\u0430\u0447\r\n\r\n*\u0420\u0435\u0437\u0443\u043b\u044c\u0442\u0430\u0442*\r\n\u041e\u0442\u043a\u0440\u044b\u0432\u0430\u0435\u0442\u0441\u044f \u0442\u0430\u0431\u043b\u0438\u0446\u0430 \"\u0437\u0430\u0434\u0430\u0447\u0438\", \u0432 Console \u043f\u043e\u044f\u0432\u043b\u044f\u0435\u0442\u0441\u044f \u043e\u0448\u0438\u0431\u043a\u0430:\r\nVM5424:1 Uncaught (in promise) SyntaxError: Unexpected token < in JSON at position 0",
            "start_date": "2022-03-17",
            "done_ratio": 0,
            "created_on": "2022-03-17T09:59:38Z",
            "updated_on": "2022-03-18T13:58:20Z"
        },
        {
            "id": 30095,
            "project": {
                "id": 503,
                "name": "\u041a\u0440\u0438\u043f\u0442\u0430"
            },
            "tracker": {
                "id": 5,
                "name": "Feature"
            },
            "status": {
                "id": 1,
                "name": "New"
            },
            "priority": {
                "id": 4,
                "name": "\u041d\u043e\u0440\u043c\u0430\u043b\u044c\u043d\u044b\u0439"
            },
            "author": {
                "id": 4,
                "name": "A.  Haletsky"
            },
            "assigned_to": {
                "id": 428,
                "name": "A. Zharikov"
            },
            "fixed_version": {
                "id": 1826,
                "name": "3"
            },
            "subject": "\u0420\u0435\u0434\u0438\u0440\u0435\u043a\u0442 \u0441 \u0433\u043b\u0430\u0432\u043d\u043e\u0439 \u0441\u0442\u0440\u0430\u043d\u0438\u0446\u044b",
            "description": "\u0414\u043b\u044f \u043c\u043e\u0431\u0438\u043b\u044c\u043d\u044b\u0445 (\u0434\u0435\u0442\u0435\u043a\u0442 \u0438 \u0440\u0435\u0434\u0438\u0440\u0435\u043a\u0442) \u0441\u0440\u0430\u0437\u0443 \u043e\u0442\u043f\u0440\u0430\u0432\u043b\u044f\u0435\u043c \u043d\u0430 \u043a\u0430\u0440\u0442\u0443 \u043f\u0440\u0438 \u0437\u0430\u0445\u043e\u0434\u0435 \u043d\u0430 \u0433\u043b\u0430\u0432\u043d\u0443\u044e (\u0435\u0441\u043b\u0438 \u043f\u043e\u043b\u044c\u0437\u043e\u0432\u0430\u0442\u0435\u043b\u044c \u0443 \u043d\u0430\u0441 \u0435\u0449\u0435 \u043d\u0435 \u0431\u044b\u043b, \u0441\u0442\u0430\u0432\u0438\u0442\u044c \u043a\u0443\u043a\u0443)",
            "start_date": "2022-03-14",
            "done_ratio": 0,
            "estimated_hours": 4.0,
            "created_on": "2022-03-14T13:56:43Z",
            "updated_on": "2022-03-14T14:00:54Z"
        },
        {
            "id": 30094,
            "project": {
                "id": 503,
                "name": "\u041a\u0440\u0438\u043f\u0442\u0430"
            },
            "tracker": {
                "id": 5,
                "name": "Feature"
            },
            "status": {
                "id": 1,
                "name": "New"
            },
            "priority": {
                "id": 4,
                "name": "\u041d\u043e\u0440\u043c\u0430\u043b\u044c\u043d\u044b\u0439"
            },
            "author": {
                "id": 4,
                "name": "A.  Haletsky"
            },
            "assigned_to": {
                "id": 428,
                "name": "A. Zharikov"
            },
            "fixed_version": {
                "id": 1826,
                "name": "3"
            },
            "subject": "\u041f\u043e\u0434\u0432\u0430\u043b \u043c\u043e\u0431\u0438\u043b\u044c\u043d\u043e\u0439 \u0432\u0435\u0440\u0441\u0438\u0438",
            "description": "\u0421\u0435\u0439\u0447\u0430\u0441 \u043f\u0435\u0440\u0435\u0433\u0440\u0443\u0436\u0435\u043d \u0441\u0441\u044b\u043b\u043a\u0430\u043c\u0438, \u0441\u0432\u0435\u0440\u043d\u0443\u0442\u044c \u043e\u0441\u0442\u0430\u0432\u0438\u0432 \u0441\u0430\u043c\u044b\u0435 \u0432\u0430\u0436\u043d\u044b\u0435 (\u044d\u0442\u043e \u043a\u0430\u043a\u0438\u0435?)\r\n\r\n\u041f\u043e\u043a\u0430 \u043e\u0441\u0442\u0430\u0432\u0438\u0442\u044c \r\nTerms of Use\r\nContact and Support\r\n\r\n\u0412\u0441\u0435 \u043e\u0441\u0442\u0430\u043b\u044c\u043d\u044b\u0435 \u0443\u043d\u0435\u0441\u0442\u0438 \u043d\u0430 \u0441\u043e\u043e\u0442\u0432\u0435\u0442\u0441\u0442\u0432\u0443\u044e\u0449\u0438\u0439 \u0441\u0442\u0440\u0430\u043d\u0438\u0446\u044b (\u043d\u0435 \u043d\u0443\u0436\u0435\u043d \u0438\u043c \u0432\u0442\u043e\u0440\u043e\u0439 \u0443\u0440\u043e\u0432\u0435\u043d\u0442)\r\n",
            "start_date": "2022-03-14",
            "done_ratio": 0,
            "estimated_hours": 4.0,
            "created_on": "2022-03-14T13:55:10Z",
            "updated_on": "2022-03-18T10:08:03Z"
        },
        {
            "id": 30093,
            "project": {
                "id": 491,
                "name": "Mail Trade CRM v.2"
            },
            "tracker": {
                "id": 1,
                "name": "Bug"
            },
            "status": {
                "id": 1,
                "name": "New"
            },
            "priority": {
                "id": 4,
                "name": "\u041d\u043e\u0440\u043c\u0430\u043b\u044c\u043d\u044b\u0439"
            },
            "author": {
                "id": 433,
                "name": "A. Stratan"
            },
            "assigned_to": {
                "id": 428,
                "name": "A. Zharikov"
            },
            "subject": "Templaise: \u041d\u0435\u0442 \u0440\u0435\u0430\u043a\u0446\u0438\u0438 \u043d\u0430 \u0441\u0442\u0440\u0435\u043b\u043a\u0443 \u0441\u043e\u0440\u0442\u0438\u0440\u043e\u0432\u043a\u0438 \u0432 \u0448\u0430\u0431\u043b\u043e\u043d\u0435",
            "description": "\u041f\u0440\u0438 \u043a\u043b\u0438\u043a\u0435 \u043d\u0430 \u0441\u0442\u0440\u0435\u043b\u043a\u0443 \u0441\u043e\u0440\u0442\u0438\u0440\u043e\u0432\u043a\u0438, \u0441\u0442\u0440\u0435\u043b\u043a\u0430 \u043f\u043e\u0432\u043e\u0440\u0430\u0447\u0438\u0432\u0430\u0435\u0442\u0441\u044f, \u043d\u043e \u043d\u0438\u0447\u0435\u0433\u043e \u043d\u0435 \u043f\u0440\u043e\u0438\u0441\u0445\u043e\u0434\u0438\u0442\r\n\r\n*\u0428\u0430\u0433\u0438 \u0432\u043e\u0441\u043f\u0440\u043e\u0438\u0437\u0432\u0435\u0434\u0435\u043d\u0438\u044f:* (\u043b\u043e\u0433\u0438\u043d admin)\r\n\r\n# http://135.181.90.157/letter_fragments_and_templates?direction=asc&page=1&per_page=15&sort=l.name\r\n# \u0428\u0430\u0431\u043b\u043e\u043d\u044b\r\n# \u041a\u043b\u0438\u043a \u043f\u043e \u0441\u0442\u0440\u0435\u043b\u043a\u0438 \u0432\u043e\u0437\u043b\u0435 \"\u0438\u043c\u044f\r\n\r\n*\u0420\u0435\u0437\u0443\u043b\u044c\u0442\u0430\u0442*\r\n\u0421\u0442\u0440\u0435\u043b\u043e\u0447\u043a\u0430 \u043a\u0440\u0443\u0442\u0438\u0442\u0441\u044f, \u043d\u043e \u0441\u043e\u0440\u0442\u0438\u0440\u043e\u0432\u043a\u0430 \u043d\u0435 \u043c\u0435\u043d\u044f\u0435\u0442\u0441\u044f\r\n\r\n*\u041e\u0436\u0438\u0434\u0430\u0435\u043c\u044b\u0439 \u0440\u0435\u0437\u0443\u043b\u044c\u0442\u0430\u0442*\r\n\u0415\u0441\u043b\u0438 \u0441\u0442\u0440\u0435\u043b\u043e\u0447\u043a\u0430 \u0435\u0441\u0442\u044c, \u0442\u043e \u043e\u043d\u0430 \u0434\u043e\u043b\u0436\u043d\u0430 \u0432\u044b\u043f\u043e\u043b\u043d\u044f\u0442\u044c \u0434\u0435\u0439\u0441\u0442\u0432\u0438\u0435 \r\n<path d=\"M20 12l-1.41-1.41L13 16.17V4h-2v12.17l-5.58-5.59L4 12l8 8 8-8z\"></path>",
            "start_date": "2022-03-14",
            "done_ratio": 0,
            "created_on": "2022-03-14T13:47:28Z",
            "updated_on": "2022-03-23T08:54:56Z"
        },
        {
            "id": 30092,
            "project": {
                "id": 503,
                "name": "\u041a\u0440\u0438\u043f\u0442\u0430"
            },
            "tracker": {
                "id": 5,
                "name": "Feature"
            },
            "status": {
                "id": 1,
                "name": "New"
            },
            "priority": {
                "id": 4,
                "name": "\u041d\u043e\u0440\u043c\u0430\u043b\u044c\u043d\u044b\u0439"
            },
            "author": {
                "id": 4,
                "name": "A.  Haletsky"
            },
            "assigned_to": {
                "id": 428,
                "name": "A. Zharikov"
            },
            "fixed_version": {
                "id": 1826,
                "name": "3"
            },
            "subject": "\u0424\u043e\u0440\u043c\u0430 \"\u0434\u043e\u0431\u0430\u0432\u0438\u0442\u044c \u043e\u0431\u044a\u0435\u043a\u0442\"",
            "description": "\u0418\u043c\u044f-\u043c\u0435\u0439\u043b + \u043e\u043f\u0438\u0441\u0430\u043d\u0438\u0435 \u043e\u0431\u044a\u0435\u043a\u0442\u0430.\r\n\u041e\u0442\u043f\u0440\u0430\u0432\u043b\u044f\u0435\u043c \u043d\u0430 \u043c\u044b\u043b\u043e \u0430\u0434\u043c\u0438\u043d\u0438\u0441\u0442\u0440\u0430\u0442\u043e\u0440\u0443, \u0431\u043e\u043b\u044c\u0448\u0435 \u043d\u0438\u0447\u0435\u0433\u043e \u043d\u0435 \u0434\u0435\u043b\u0430\u0435\u043c, \u043f\u0443\u0441\u0442\u044c \u0440\u0430\u0437\u0433\u0440\u0435\u0431\u0430\u044e\u0442 \u0440\u0443\u043a\u0430\u043c\u0438.\r\n\u041a\u043e\u0433\u0434\u0430 \u043d\u0430\u0431\u0435\u0440\u0435\u0442\u0441\u044f \u0431\u043e\u043b\u0435\u0435-\u043c\u0435\u043d\u0435\u0435 \u043a\u043e\u043b\u0438\u0447\u0435\u0441\u0442\u0432\u043e - \u0432\u0435\u0440\u043d\u0435\u043c\u0441\u044f \u043a \u043a\u0430\u0431\u0438\u043d\u0435\u0442\u0443.",
            "start_date": "2022-03-14",
            "done_ratio": 0,
            "estimated_hours": 3.0,
            "created_on": "2022-03-14T13:44:51Z",
            "updated_on": "2022-03-14T13:44:51Z"
        },
        {
            "id": 30091,
            "project": {
                "id": 503,
                "name": "\u041a\u0440\u0438\u043f\u0442\u0430"
            },
            "tracker": {
                "id": 5,
                "name": "Feature"
            },
            "status": {
                "id": 1,
                "name": "New"
            },
            "priority": {
                "id": 4,
                "name": "\u041d\u043e\u0440\u043c\u0430\u043b\u044c\u043d\u044b\u0439"
            },
            "author": {
                "id": 4,
                "name": "A.  Haletsky"
            },
            "assigned_to": {
                "id": 428,
                "name": "A. Zharikov"
            },
            "fixed_version": {
                "id": 1826,
                "name": "3"
            },
            "subject": "\u0423\u0431\u0440\u0430\u0442\u044c \u0430\u0432\u0442\u043e\u0440\u0438\u0437\u0430\u0446\u0438\u044e \u0434\u043b\u044f \u0438\u0441\u043f\u043e\u043b\u044c\u0437\u043e\u0432\u0430\u043d\u0438\u044f \u043a\u0430\u0440\u0442\u044b",
            "description": "\u041d\u0435 \u0442\u0440\u0435\u0431\u043e\u0432\u0430\u0442\u044c \u0437\u0430\u0440\u0435\u0433\u0438\u0441\u0442\u0440\u0438\u0440\u043e\u0432\u0430\u0442\u044c\u0441\u044f, \u0442\u043e\u043b\u044c\u043a\u043e \u043f\u0440\u0438 \u043f\u043e\u043f\u044b\u0442\u043a\u0435 \u0438\u0441\u043f\u043e\u043b\u044c\u0437\u043e\u0432\u0430\u0442\u044c \u0444\u0443\u043d\u0446\u0438\u043e\u043d\u0430\u043b \u0441\u0432\u044f\u0437\u0430\u043d\u043d\u044b\u0439 \u0441 \u0430\u043a\u043a\u0430\u0443\u043d\u0442\u043e\u043c \u0432\u044b\u0434\u0430\u0432\u0430\u0442\u044c \u043c\u043e\u0434\u0430\u043b\u043a\u0443 \u0430\u0432\u0442\u043e\u0440\u0438\u0437\u0430\u0446\u0438\u0438 (\u0432 \u0442.\u0447. \u0447\u0435\u0440\u0435\u0437 \u0441\u043e\u0446. \u0441\u0435\u0442\u0438 \u0441 \u0431\u044b\u0441\u0442\u0440\u043e\u0439 \u0440\u0435\u0433\u0438\u0441\u0442\u0440\u0430\u0446\u0438\u0435\u0439)",
            "start_date": "2022-03-14",
            "done_ratio": 0,
            "estimated_hours": 12.0,
            "created_on": "2022-03-14T13:32:19Z",
            "updated_on": "2022-03-21T10:53:05Z"
        },
        {
            "id": 30090,
            "project": {
                "id": 503,
                "name": "\u041a\u0440\u0438\u043f\u0442\u0430"
            },
            "tracker": {
                "id": 5,
                "name": "Feature"
            },
            "status": {
                "id": 1,
                "name": "New"
            },
            "priority": {
                "id": 4,
                "name": "\u041d\u043e\u0440\u043c\u0430\u043b\u044c\u043d\u044b\u0439"
            },
            "author": {
                "id": 4,
                "name": "A.  Haletsky"
            },
            "assigned_to": {
                "id": 428,
                "name": "A. Zharikov"
            },
            "fixed_version": {
                "id": 1826,
                "name": "3"
            },
            "subject": "Call link \u043d\u0430 \u0442\u0435\u043b\u0435\u0444\u043e\u043d",
            "description": "\u0418\u0437 \u043a\u0430\u0440\u0442\u043e\u0447\u0435\u043a \u0438 \u0432\u0435\u0437\u0434\u0435 \u0433\u0434\u0435 \u0437\u0430\u043c\u0435\u0442\u0438\u043c",
            "start_date": "2022-03-14",
            "done_ratio": 0,
            "estimated_hours": 2.0,
            "created_on": "2022-03-14T13:25:25Z",
            "updated_on": "2022-03-14T13:25:25Z"
        }
    ],
    "total_count": 60,
    "offset": 0,
    "limit": 25
}